{
  "feeds": [
    {
      "id": "69afad2b00000000220221e8",
      "xsecToken": "ABD0pLkCK9G79vgh5wfrYAv1eMqTvPLVj4JoqybcjxWfs=",
      "modelType": "note",
      "index": 0,
      "displayTitle": "亲测是珠海长隆最有效路线",
      "type": "normal",
      "user": {
        "userId": "63f63624000000001001e139",
        "nickname": "BADUN"
      },
      "interactInfo": {
        "likedCount": "864",
        "collectedCount": "1036",
        "commentCount": "14",
        "sharedCount": "505"
      },
      "cover": "http://sns-webpic-qc.xhscdn.com/202604150008/509da411792f03c32710e5debe071441/1040g00831th591vj6e005ovm6oi43o9pm444o90!nc_n_webp_mw_1"
    },
    {
      "id": "698d675d000000001600ae6f",
      "xsecToken": "AB-qt3VxC3Ftw2VP1IuYQPB4NM__f4g-obujfvTmpnkXg=",
      "modelType": "note",
      "index": 1,
      "displayTitle": "珠海长隆少排队线路｜放假高峰期亲测",
      "type": "normal",
      "user": {
        "userId": "6725a506000000001d02d26e",
        "nickname": "爬坡喘成狗"
      },
      "interactInfo": {
        "likedCount": "2233",
        "collectedCount": "3286",
        "commentCount": "167",
        "sharedCount": "1783"
      },
      "cover": "http://sns-webpic-qc.xhscdn.com/202604150008/56030f49123d2a020d7b3c9dac1be5c8/1040g2sg31sfhutrq5mm05pp5kk37dkjebu67698!nc_n_webp_mw_1"
    },
    {
      "id": "686ce5c60000000010011ee3",
      "xsecToken": "AByrrQf2KCVoDXQapx0LvDsojTO4kOHg1bA6-MLCbdtIo=",
      "modelType": "note",
      "index": 2,
      "displayTitle": "为什么[失望R]xhs说去珠海长隆一定不能早起",
      "type": "normal",
      "user": {
        "userId": "681c4a1a000000000d008a8f",
        "nickname": "🐯长隆活地图-小雪"
      },
      "interactInfo": {
        "likedCount": "543",
        "collectedCount": "611",
        "commentCount": "1",
        "sharedCount": "176"
      },
      "cover": "http://sns-webpic-qc.xhscdn.com/202604150008/c30ac2fe1f5152b314d216c3ed409b76/notes_pre_post/1040g3k831jm196es2gdg5q0s98d392kf8psoce8!nc_n_webp_mw_1"
    },
    {
      "id": "69d8eff9000000002300795c",
      "xsecToken": "AB8ySucOcbcRMhIbecvEIByxrpdIakglr1MtzgmvgsP20=",
      "modelType": "note",
      "index": 3,
      "displayTitle": "珠海长隆三天两晚攻略",
      "type": "normal",
      "user": {
        "userId": "550f8c1ca46e963bf45eff2b",
        "nickname": "jingjing"
      },
      "interactInfo": {
        "likedCount": "33",
        "collectedCount": "42",
        "commentCount": "9",
        "sharedCount": "12"
      },
      "cover": "http://sns-webpic-qc.xhscdn.com/202604150008/ec5eb1c3bea153754ef357cda2b62a10/notes_pre_post/1040g3k031uph323iig0040928q61pvpbrk6rqco!nc_n_webp_mw_1"
    },
    {
      "id": "699c01bb000000001a02e940",
      "xsecToken": "ABaxlcLZ4W7uCvYAZ0FmEsyTtThyK-tW8vZ90x2KScuwY=",
      "modelType": "note",
      "index": 4,
      "displayTitle": "珠海长隆海洋王国，真心觉得有些无聊",
      "type": "normal",
      "user": {
        "userId": "5b928c3293055c00013bd2dd",
        "nickname": "喵喵不是猫"
      },
      "interactInfo": {
        "likedCount": "1341",
        "collectedCount": "744",
        "commentCount": "1585",
        "sharedCount": "425"
      },
      "cover": "http://sns-webpic-qc.xhscdn.com/202604150008/756133827ad587171f491560cedeba0e/1040g00831stvnck462004as3g9635kmt6ok73rg!nc_n_webp_mw_1"
    },
    {
      "id": "69970f2e000000000c037927",
      "xsecToken": "ABuYWcPhBoWeXktgaI8UCVs6gdRSdjMvJytKrSu2ntJWk=",
      "modelType": "note",
      "index": 5,
      "displayTitle": "珠海长隆，早知道我就不去了！",
      "type": "normal",
      "user": {
        "userId": "634a69b1000000001802efe1",
        "nickname": "Gemini星星子"
      },
      "interactInfo": {
        "likedCount": "110",
        "collectedCount": "38",
        "commentCount": "341",
        "sharedCount": "78"
      },
      "cover": "http://sns-webpic-qc.xhscdn.com/202604150008/bd9fc8bcda4a97e88c311204700a9061/notes_uhdr/1040g3qg31sp6quhp5c005oqad6om5rv1vlt68vg!nc_n_webp_mw_1"
    },
    {
      "id": "515f8073-b6dc-42f6-b95a-82f6b570ea1d#1776182900716",
      "xsecToken": "ABRA5uhN4MxFRhGXdW_5aO0OW25HTPEdKOs16F_uIWOGStj-kxRl5XmMXfzlQKFJNLSh3TFWNshzNFVbq3GZgsT6pwTFOGrUyP88NrGZ34jVQ=",
      "modelType": "hot_query",
      "index": 6,
      "displayTitle": "",
      "type": "",
      "user": {
        "userId": "",
        "nickname": ""
      },
      "interactInfo": {
        "likedCount": "",
        "collectedCount": "",
        "commentCount": "",
        "sharedCount": ""
      }
    },
    {
      "id": "69817821000000001a036a6e",
      "xsecToken": "AB6jIvQ4eDdjgZeNOBkmlpOXNg41bd3OEtwsHFDaCyOPo=",
      "modelType": "note",
      "index": 7,
      "displayTitle": "2岁女孩珠海长隆海洋王国游玩路线",
      "type": "normal",
      "user": {
        "userId": "5a5c75d24eacab7c409348d4",
        "nickname": "星星收进眼"
      },
      "interactInfo": {
        "likedCount": "2658",
        "collectedCount": "3262",
        "commentCount": "80",
        "sharedCount": "1223"
      },
      "cover": "http://sns-webpic-qc.xhscdn.com/202604150008/1033c087db5159fe00447a10aaaac8e4/notes_pre_post/1040g3k831s4408c25mb04a0rs2qt4i6k2hucm80!nc_n_webp_mw_1"
    },
    {
      "id": "699a69b1000000001a02d9da",
      "xsecToken": "ABLpyrAGNhJWJvQjviay_JeJeLGxzYanRdeKXZfOhp2N4=",
      "modelType": "note",
      "index": 8,
      "displayTitle": "珠海长隆真的不用早起排队",
      "type": "normal",
      "user": {
        "userId": "5e1d91f4000000000100b255",
        "nickname": "Annie✨"
      },
      "interactInfo": {
        "likedCount": "35",
        "collectedCount": "30",
        "commentCount": "0",
        "sharedCount": "11"
      },
      "cover": "http://sns-webpic-qc.xhscdn.com/202604150008/7237da71fec294019cbb8fed7bef1d99/1040g00831sseebka686g5ngti7q09cil795rgog!nc_n_webp_mw_1"
    },
    {
      "id": "699e86bb000000002801fe02",
      "xsecToken": "ABUrc5z1P0QKqiOhqUZV4I50-A318fx4awMqzz8MS4tOY=",
      "modelType": "note",
      "index": 9,
      "displayTitle": "一定要看（珠海4天3晚），领导都说好的攻略～",
      "type": "normal",
      "user": {
        "userId": "54f3cea44fac636367c1424c",
        "nickname": "又又又又去自驾啦"
      },
      "interactInfo": {
        "likedCount": "138",
        "collectedCount": "274",
        "commentCount": "20",
        "sharedCount": "57"
      },
      "cover": "http://sns-webpic-qc.xhscdn.com/202604150008/76016652ed7c70939ec864c8a4353569/1040g2sg31t0g19anlse0401qrn7a8gice9i6920!nc_n_webp_mw_1"
    },
    {
      "id": "699873f8000000001b014a5c",
      "xsecToken": "ABV2DRoqELAF6fwjtqswAtSqSLbwsQISptfejSVgthsO4=",
      "modelType": "note",
      "index": 10,
      "displayTitle": "珠海长隆避雷帖",
      "type": "normal",
      "user": {
        "userId": "564eab53b7ba222880f9bb48",
        "nickname": "想不到一个名字"
      },
      "interactInfo": {
        "likedCount": "27",
        "collectedCount": "12",
        "commentCount": "71",
        "sharedCount": "13"
      },
      "cover": "http://sns-webpic-qc.xhscdn.com/202604150008/60cfaecd551c45063b15cacf5ae01ba7/1040g00831sqi0u9c680042lhdull7eq8pc2ivmo!nc_n_webp_mw_1"
    },
    {
      "id": "69c3a7a0000000001a026e94",
      "xsecToken": "ABytn4YjY4PWKmHx-qA47BVwcXoiw1nG6ZqXQeH9IlZYQ=",
      "modelType": "note",
      "index": 11,
      "displayTitle": "亲测体验 | 珠海长隆vs广州长隆",
      "type": "normal",
      "user": {
        "userId": "5bd6323cd39b5e00013de7f9",
        "nickname": "大胖与阿钦"
      },
      "interactInfo": {
        "likedCount": "63",
        "collectedCount": "31",
        "commentCount": "3",
        "sharedCount": "70"
      },
      "cover": "http://sns-webpic-qc.xhscdn.com/202604150008/a322c7d16969634135318ba15dce939e/1040g2sg31u4n265liqa04blhjop3ppvplog8j0o!nc_n_webp_mw_1"
    },
    {
      "id": "69b8280a00000000220034f6",
      "xsecToken": "ABviZtLbfPS8Ov0HAcX527P68qANDgUr6dg9mT-vnyn0M=",
      "modelType": "note",
      "index": 12,
      "displayTitle": "珠海长隆 我给到夯极了！",
      "type": "normal",
      "user": {
        "userId": "632432d8000000002303cd70",
        "nickname": "Stuart"
      },
      "interactInfo": {
        "likedCount": "151",
        "collectedCount": "120",
        "commentCount": "4",
        "sharedCount": "77"
      },
      "cover": "http://sns-webpic-qc.xhscdn.com/202604150008/229be272b6b462d3a18c40ebb2573c13/notes_uhdr/1040g3qo31tph3e87ne005op46bc8vjbgj2rhv20!nc_n_webp_mw_1"
    },
    {
      "id": "694ec992000000001e02040c",
      "xsecToken": "ABuw0RkPyxh3T--72cmYHTg74gNoftm1EEPJT45FhLyNY=",
      "modelType": "note",
      "index": 13,
      "displayTitle": "珠海长隆真的挺一般",
      "type": "normal",
      "user": {
        "userId": "56bf264e6a6a691fe8b64ba3",
        "nickname": "西米"
      },
      "interactInfo": {
        "likedCount": "230",
        "collectedCount": "64",
        "commentCount": "379",
        "sharedCount": "106"
      },
      "cover": "http://sns-webpic-qc.xhscdn.com/202604150008/c7432e1884b6baa8bef83c1c1efba696/note_pre_post_uhdr/1040g3r831qik95fh0a0045il27j4sit3988sa0g!nc_n_webp_mw_1"
    },
    {
      "id": "6999d947000000001a023148",
      "xsecToken": "ABaWvjjEQhjaFP7uvRlJcpThJyCphRULdOt2hH5gXXFl8=",
      "modelType": "note",
      "index": 14,
      "displayTitle": "晚上8点以后的海洋王国真香啊",
      "type": "normal",
      "user": {
        "userId": "5a410e154eacab12dfcb307c",
        "nickname": "大喜"
      },
      "interactInfo": {
        "likedCount": "26",
        "collectedCount": "19",
        "commentCount": "21",
        "sharedCount": "17"
      },
      "cover": "http://sns-webpic-qc.xhscdn.com/202604150008/a0d949c42874cf4f6c8d6d3d9502695e/1040g2sg31srts84hlsdg4a0fqe71ac3st5vte30!nc_n_webp_mw_1"
    },
    {
      "id": "69ce7afd000000001b003667",
      "xsecToken": "AB5HHOUYDVTMCIlB_MmqD2Gb-94byqvxrzIX1uvS56AHo=",
      "modelType": "note",
      "index": 15,
      "displayTitle": "珠海长隆2次之旅的攻略总结心得❤️",
      "type": "normal",
      "user": {
        "userId": "5b538074e8ac2b16d4d62b6f",
        "nickname": "菠萝🍍妈的带娃日常"
      },
      "interactInfo": {
        "likedCount": "14",
        "collectedCount": "13",
        "commentCount": "11",
        "sharedCount": "5"
      },
      "cover": "http://sns-webpic-qc.xhscdn.com/202604150008/c767d4824c358b9a9964f8883c11d76e/notes_pre_post/1040g3k831uf8fcdvhm9g4a7cir078arfkippph0!nc_n_webp_mw_1"
    },
    {
      "id": "515f8073-b6dc-42f6-b95a-82f6b570ea1d#1776182900716",
      "xsecToken": "ABRA5uhN4MxFRhGXdW_5aO0OW25HTPEdKOs16F_uIWOGStj-kxRl5XmMXfzlQKFJNLSh3TFWNshzNFVbq3GZgsT6pwTFOGrUyP88NrGZ34jVQ=",
      "modelType": "hot_query",
      "index": 16,
      "displayTitle": "",
      "type": "",
      "user": {
        "userId": "",
        "nickname": ""
      },
      "interactInfo": {
        "likedCount": "",
        "collectedCount": "",
        "commentCount": "",
        "sharedCount": ""
      }
    },
    {
      "id": "691adf250000000007035d6b",
      "xsecToken": "ABR-cYjr-HRBd-ggZ1OUsJ2oJkjsb-Vp9VgAXd_tkMkkw=",
      "modelType": "note",
      "index": 17,
      "displayTitle": "玩珠海长隆✨ 2 日游",
      "type": "normal",
      "user": {
        "userId": "5c204e610000000007006d73",
        "nickname": "雨杉不乖张"
      },
      "interactInfo": {
        "likedCount": "308",
        "collectedCount": "485",
        "commentCount": "33",
        "sharedCount": "227"
      },
      "cover": "http://sns-webpic-qc.xhscdn.com/202604150008/f52f13d70ae4c6a3251a13a10e9acb8d/notes_pre_post/1040g3k831ovtd4fp10305n109pghorbjbrsnge0!nc_n_webp_mw_1"
    },
    {
      "id": "69a2e1b9000000002800bbf6",
      "xsecToken": "ABzAbXbR-QgOr8PomDLcNMFcyltzY-_I8q8FuEQaZxXss=",
      "modelType": "note",
      "index": 18,
      "displayTitle": "珠海长隆两日游心得汇总",
      "type": "normal",
      "user": {
        "userId": "5d526a940000000016018d0f",
        "nickname": "♥♥♥♥♥♥"
      },
      "interactInfo": {
        "likedCount": "148",
        "collectedCount": "260",
        "commentCount": "11",
        "sharedCount": "57"
      },
      "cover": "http://sns-webpic-qc.xhscdn.com/202604150008/b42147acfd5ea81e0c75632189de3b9c/1040g2sg31t4nf0sj62ig5naidaa5j38ffealaf0!nc_n_webp_mw_1"
    },
    {
      "id": "694ea605000000001e0066d2",
      "xsecToken": "ABuw0RkPyxh3T--72cmYHTg2nuQJHKyotvwja3jVpUQdY=",
      "modelType": "note",
      "index": 19,
      "displayTitle": "刚从珠海长隆海洋王国回来，说点大实话‼️",
      "type": "normal",
      "user": {
        "userId": "6822fcfe000000000e011359",
        "nickname": "南京小胖西"
      },
      "interactInfo": {
        "likedCount": "26",
        "collectedCount": "19",
        "commentCount": "3",
        "sharedCount": "9"
      },
      "cover": "http://sns-webpic-qc.xhscdn.com/202604150008/e2fe427a685978743990b79b4ecd4b60/1040g2sg31qif65k6gm305q12vjv3i4qpeqj785g!nc_n_webp_mw_1"
    },
    {
      "id": "69719ce3000000000a03343c",
      "xsecToken": "AB1GJxW4G2gMZOpOtbf-KH6fuFh7-O4Yj1UecwP1ydUwQ=",
      "modelType": "note",
      "index": 20,
      "displayTitle": "珠海长隆攻略（纯个人分享）",
      "type": "normal",
      "user": {
        "userId": "5a924628b1da142a178571fc",
        "nickname": "阳阳妈育儿"
      },
      "interactInfo": {
        "likedCount": "83",
        "collectedCount": "131",
        "commentCount": "29",
        "sharedCount": "37"
      },
      "cover": "http://sns-webpic-qc.xhscdn.com/202604150008/209cf94d69790f7836e7d0b915f47dfb/1040g2sg31rkjchs522004a296m32gsfs5rjlhog!nc_n_webp_mw_1"
    },
    {
      "id": "6938fa34000000001f006dcf",
      "xsecToken": "AB5VFAC0tEvvPwnFMVa0a13wk73ofIjRDxxQrw_UvDrWs=",
      "modelType": "note",
      "index": 21,
      "displayTitle": "珠海长隆劝退",
      "type": "normal",
      "user": {
        "userId": "5b5c8b9411be1012cf9ac78a",
        "nickname": "路路"
      },
      "interactInfo": {
        "likedCount": "62",
        "collectedCount": "18",
        "commentCount": "148",
        "sharedCount": "37"
      },
      "cover": "http://sns-webpic-qc.xhscdn.com/202604150008/581efa22ca30fdaba8e8fefdf6d02697/note_pre_post_uhdr/1040g3r831pt99qtdkgd04a7kd15p9hsahifn7q0!nc_n_webp_mw_1"
    },
    {
      "id": "67b08b0400000000180129f3",
      "xsecToken": "ABueL-HdkPi9ts97bNN4kI7-wdQCAcpaquSH_7YEj4oS4=",
      "modelType": "note",
      "index": 22,
      "displayTitle": "刚从长隆回来，千字攻略玩转海洋王国😎",
      "type": "normal",
      "user": {
        "userId": "5e98286f0000000001002604",
        "nickname": "航海导览家"
      },
      "interactInfo": {
        "likedCount": "380",
        "collectedCount": "500",
        "commentCount": "3",
        "sharedCount": "315"
      },
      "cover": "http://sns-webpic-qc.xhscdn.com/202604150008/532a937733cfc4e13b32036653838c2f/1040g00831du36ic00k6g5nko51ng89g4vhg1efo!nc_n_webp_mw_1"
    },
    {
      "id": "699879f9000000000a02ef9c",
      "xsecToken": "ABV2DRoqELAF6fwjtqswAtSrPaGg4t6psDn8m-7GIjcZQ=",
      "modelType": "note",
      "index": 23,
      "displayTitle": "珠海长隆海洋王国就走这条路线，松弛逛完！",
      "type": "normal",
      "user": {
        "userId": "62edcbdd000000001f007f43",
        "nickname": "Ju"
      },
      "interactInfo": {
        "likedCount": "224",
        "collectedCount": "196",
        "commentCount": "2",
        "sharedCount": "62"
      },
      "cover": "http://sns-webpic-qc.xhscdn.com/202604150008/5cf1bb10c7553891030a750c5b417514/notes_pre_post/1040g3k031uii1hi91m105ondpfenovq3bism1o8!nc_n_webp_mw_1"
    },
    {
      "id": "69998f6c0000000015023aa1",
      "xsecToken": "ABaWvjjEQhjaFP7uvRlJcpTsLv40wKhG7GY63JgDxSRQA=",
      "modelType": "note",
      "index": 24,
      "displayTitle": "长隆海洋王国，赚钱吃相太难看了",
      "type": "normal",
      "user": {
        "userId": "59872d015e87e75b92ad56ed",
        "nickname": "脆皮小烤肠"
      },
      "interactInfo": {
        "likedCount": "162",
        "collectedCount": "38",
        "commentCount": "633",
        "sharedCount": "50"
      },
      "cover": "http://sns-webpic-qc.xhscdn.com/202604150008/2284d52ffd31090c98997e42114871e2/notes_uhdr/1040g3qg31srkvvkf5m1049nh0smg2lndm10nqgg!nc_n_webp_mw_1"
    },
    {
      "id": "69b7f4cd0000000022001dd6",
      "xsecToken": "ABzF2CZYA7Amvn51hRiF54mU1P27DAihqNSTOGJ9wmuMY=",
      "modelType": "note",
      "index": 25,
      "displayTitle": "",
      "type": "normal",
      "user": {
        "userId": "5ba5dc779c1a5300015295e0",
        "nickname": "两颗涵涵糖"
      },
      "interactInfo": {
        "likedCount": "263",
        "collectedCount": "360",
        "commentCount": "3",
        "sharedCount": "120"
      },
      "cover": "http://sns-webpic-qc.xhscdn.com/202604150008/6428a687ab8e5db6efd7999addaf9f3d/notes_pre_post/1040g3k031tparhvrnq6g4b3t6le7f5f0e113470!nc_n_webp_mw_1"
    },
    {
      "id": "6904dbef000000000700afc6",
      "xsecToken": "ABye-u6Hl-men9_xn5P_SAUKShkvznp77A0wo1i8-NF-4=",
      "modelType": "note",
      "index": 26,
      "displayTitle": "去珠海长隆一定要注意的5⃣️件事",
      "type": "normal",
      "user": {
        "userId": "5959f5ca6a6a6923aa31325b",
        "nickname": "芒果盐汽水🥤"
      },
      "interactInfo": {
        "likedCount": "45",
        "collectedCount": "14",
        "commentCount": "12",
        "sharedCount": "12"
      },
      "cover": "http://sns-webpic-qc.xhscdn.com/202604150008/00aaaf28fa923ee06e4dc4cff6a54343/notes_pre_post/1040g3k831oadsg834u7049l9a4qskcir4hspmno!nc_n_webp_mw_1"
    },
    {
      "id": "68f5cebd00000000070099fa",
      "xsecToken": "ABhz7LV05FXFJTPnzxCNhd6-GzcpOKjuQABrHh6hZmo8U=",
      "modelType": "note",
      "index": 27,
      "displayTitle": "珠海长隆 2天1晚 超详攻略亲测不绕路！",
      "type": "normal",
      "user": {
        "userId": "63d8f020000000002600565b",
        "nickname": "垂涎自由的鸟_"
      },
      "interactInfo": {
        "likedCount": "340",
        "collectedCount": "310",
        "commentCount": "50",
        "sharedCount": "170"
      },
      "cover": "http://sns-webpic-qc.xhscdn.com/202604150008/e7072ffbc1424dbe8af8f0c1e3206e67/notes_pre_post/1040g3k831nrpvhcu6mcg5ouou0g9glir34sbm88!nc_n_webp_mw_1"
    },
    {
      "id": "253a60f0-e69d-46c2-adc8-840cf5472312#1776182901523",
      "xsecToken": "ABX5osWzIRcGJZCsTDosAPs60QcOWXQLllC0cuv4HLttUfBmkzBLUDv29ScMSDL6zVdoNG28saGTkGy2pKxBwW-JqXujl4rj21QfuJt3GhW1s=",
      "modelType": "hot_query",
      "index": 28,
      "displayTitle": "",
      "type": "",
      "user": {
        "userId": "",
        "nickname": ""
      },
      "interactInfo": {
        "likedCount": "",
        "collectedCount": "",
        "commentCount": "",
        "sharedCount": ""
      }
    },
    {
      "id": "68c4f7fb000000001b02318e",
      "xsecToken": "ABw3pBkdmMD9M3qj87Qkm0EOs6PffYNYY1hY8vt1szvV0=",
      "modelType": "note",
      "index": 29,
      "displayTitle": "经常带团去长隆海洋王国的导游真心建议…",
      "type": "normal",
      "user": {
        "userId": "683bfb20000000001d016d22",
        "nickname": "Jack F'''"
      },
      "interactInfo": {
        "likedCount": "76",
        "collectedCount": "75",
        "commentCount": "13",
        "sharedCount": "24"
      },
      "cover": "http://sns-webpic-qc.xhscdn.com/202604150008/7f8b83880b71cae37ea91bd6cbb4c48d/notes_pre_post/1040g3k831mc1g9nhm8c05q1rvcg7ar92ejknptg!nc_n_webp_mw_1"
    },
    {
      "id": "68edf91c0000000003020a60",
      "xsecToken": "ABf01Bc37YWvJv3mGUd38fix2SkWrI3A4uE1L2iu1Lrm4=",
      "modelType": "note",
      "index": 30,
      "displayTitle": "珠海长隆最值得花钱的项目",
      "type": "normal",
      "user": {
        "userId": "58ce32af37cec92c2f55abd5",
        "nickname": "没事改改名字"
      },
      "interactInfo": {
        "likedCount": "20",
        "collectedCount": "7",
        "commentCount": "20",
        "sharedCount": "7"
      },
      "cover": "http://sns-webpic-qc.xhscdn.com/202604150008/b65241254ec8050979853dda56f0d4ad/1040g00831nk2md3a586g49ajakpavaul07ert60!nc_n_webp_mw_1"
    },
    {
      "id": "69ddab2f0000000022029275",
      "xsecToken": "ABHy1Np5g_yLamV2a7Ld59zr-bpmrGrRrESV2XJy9RG9I=",
      "modelType": "note",
      "index": 31,
      "displayTitle": "4月14日珠海长隆实况！",
      "type": "normal",
      "user": {
        "userId": "5cf7d3da0000000012038366",
        "nickname": "珠海长隆钰钰童车出租"
      },
      "interactInfo": {
        "likedCount": "2",
        "collectedCount": "1",
        "commentCount": "0",
        "sharedCount": "0"
      },
      "cover": "http://sns-webpic-qc.xhscdn.com/202604150008/1f85459f9b1de84e328d26287fe97482/1040g00831uu3t59sjq405n7nqfd4n0r6thanckg!nc_n_webp_mw_1"
    },
    {
      "id": "6866526c000000002201eb9a",
      "xsecToken": "ABZJh0Avp2nADEsuiwdvKen0AZGsQpcx8I2NX_84DXCt0=",
      "modelType": "note",
      "index": 32,
      "displayTitle": "珠海刚回，说说珠海长隆的经验8️⃣",
      "type": "normal",
      "user": {
        "userId": "64df13d60000000001010325",
        "nickname": "躺在橙树下吃🍊"
      },
      "interactInfo": {
        "likedCount": "442",
        "collectedCount": "421",
        "commentCount": "51",
        "sharedCount": "72"
      },
      "cover": "http://sns-webpic-qc.xhscdn.com/202604150008/5c27f14f725ac0aa4ab44c873ebfcc07/notes_pre_post/1040g3k831jfj7lii34gg5p6v2fb0a0p5b4icgp0!nc_n_webp_mw_1"
    },
    {
      "id": "68e23e930000000005038543",
      "xsecToken": "ABft4tn4J0XjnArk6xz0GP-R_O5MLrJm0Yp9mkg9V7c-U=",
      "modelType": "note",
      "index": 33,
      "displayTitle": "珠海长隆海洋王国 国庆游玩感受 6.6/10 分",
      "type": "normal",
      "user": {
        "userId": "6364d506000000001f01da11",
        "nickname": "虫二"
      },
      "interactInfo": {
        "likedCount": "100",
        "collectedCount": "51",
        "commentCount": "14",
        "sharedCount": "111"
      },
      "cover": "http://sns-webpic-qc.xhscdn.com/202604150008/bfdc34af0ce44d654d54f4ca1e1da8c1/1040g00831n8jjdca583g5or4qk37rmghsov6ng0!nc_n_webp_mw_1"
    },
    {
      "id": "68064c5b000000001c0315d2",
      "xsecToken": "ABn-B2VS_WDLsUvOr0BanfHqmj5iQHhsywIX10tS9SQ0g=",
      "modelType": "note",
      "index": 34,
      "displayTitle": "直说了，夜宿鲸鲨馆才是长隆最值的项目（live",
      "type": "normal",
      "user": {
        "userId": "648e897d000000000f005aa5",
        "nickname": "cocobrick"
      },
      "interactInfo": {
        "likedCount": "12976",
        "collectedCount": "10988",
        "commentCount": "1454",
        "sharedCount": "22440"
      },
      "cover": "http://sns-webpic-qc.xhscdn.com/202604150008/83aed3d39203373c0eb93b97a9d48179/1040g2sg31gkl1eskk2005p4eh5ujoml5oeeqqao!nc_n_webp_mw_1"
    },
    {
      "id": "69dcf322000000002200e633",
      "xsecToken": "ABJZF46Jk75kY30pt9D-Y9f7DkvuEuxsoS9ETvLPUel6s=",
      "modelType": "note",
      "index": 35,
      "displayTitle": "珠海长隆海洋王国🗺️4-14游玩必备路线攻略",
      "type": "normal",
      "user": {
        "userId": "60c02ba3000000000100a6f6",
        "nickname": "珠海长隆游玩攻略"
      },
      "interactInfo": {
        "likedCount": "6",
        "collectedCount": "12",
        "commentCount": "0",
        "sharedCount": "1"
      },
      "cover": "http://sns-webpic-qc.xhscdn.com/202604150008/0a02495199f46c388ef284273badb580/notes_pre_post/1040g3k831uteqkok2s2g5o605ehg99nmjc5oef0!nc_n_webp_mw_1"
    },
    {
      "id": "688cc5c50000000025018847",
      "xsecToken": "ABGeIbY7WmPyEzDO-3ySQGIPK-5pU_Z5UMK7aL9Xgw2Ks=",
      "modelType": "note",
      "index": 36,
      "displayTitle": "",
      "type": "normal",
      "user": {
        "userId": "5be672560a30f700017b2a71",
        "nickname": "Lil -"
      },
      "interactInfo": {
        "likedCount": "36",
        "collectedCount": "25",
        "commentCount": "35",
        "sharedCount": "3"
      },
      "cover": "http://sns-webpic-qc.xhscdn.com/202604150008/5cf8141e88925e7030efd08c606dc76c/1040g2sg31kl5buh92g704bpeqlp5cajhf20g6to!nc_n_webp_mw_1"
    },
    {
      "id": "68ac393a000000001b0346f8",
      "xsecToken": "ABT7zo7NdojCixP0Y5M88bRUIg8ncTX1iTGTVlwS_Hdl0=",
      "modelType": "note",
      "index": 37,
      "displayTitle": "去了一趟珠海长隆才知道到底有多坑！",
      "type": "normal",
      "user": {
        "userId": "5acf281b11be1019cad4c50b",
        "nickname": "珍_Queen"
      },
      "interactInfo": {
        "likedCount": "50",
        "collectedCount": "23",
        "commentCount": "154",
        "sharedCount": "11"
      },
      "cover": "http://sns-webpic-qc.xhscdn.com/202604150008/52c49b2e6695dc347f0572acdf5e3d72/1040g00831ljs2snkl80g4a4fkqk1nh8bjc8ndeg!nc_n_webp_mw_1"
    },
    {
      "id": "253a60f0-e69d-46c2-adc8-840cf5472312#1776182901523",
      "xsecToken": "ABX5osWzIRcGJZCsTDosAPs60QcOWXQLllC0cuv4HLttUfBmkzBLUDv29ScMSDL6zVdoNG28saGTkGy2pKxBwW-JqXujl4rj21QfuJt3GhW1s=",
      "modelType": "hot_query",
      "index": 38,
      "displayTitle": "",
      "type": "",
      "user": {
        "userId": "",
        "nickname": ""
      },
      "interactInfo": {
        "likedCount": "",
        "collectedCount": "",
        "commentCount": "",
        "sharedCount": ""
      }
    },
    {
      "id": "683e57e7000000000c03b704",
      "xsecToken": "ABIfFJSj7j0U8Kdyg7AZC6Y8sYwI--T3zX-siarf6o0kg=",
      "modelType": "note",
      "index": 39,
      "displayTitle": "鹦鹉过山车刷了三次，为啥没什么人排队？",
      "type": "normal",
      "user": {
        "userId": "5c6fe7b10000000011021b81",
        "nickname": "Believer"
      },
      "interactInfo": {
        "likedCount": "1282",
        "collectedCount": "256",
        "commentCount": "1098",
        "sharedCount": "1963"
      },
      "cover": "http://sns-webpic-qc.xhscdn.com/202604150008/931d2c0f5d8793a2da1c3ea777affe96/notes_pre_post/1040g3k031i8icstu78005n3fsuokc6s121dlrq8!nc_n_webp_mw_1"
    },
    {
      "id": "68ac1b37000000001c006798",
      "xsecToken": "ABT7zo7NdojCixP0Y5M88bRfoaY8tMXCLYFEfoD6bVnGw=",
      "modelType": "note",
      "index": 40,
      "displayTitle": "珠海长隆的后劲",
      "type": "normal",
      "user": {
        "userId": "5ed1336b0000000001003f16",
        "nickname": "T."
      },
      "interactInfo": {
        "likedCount": "110",
        "collectedCount": "53",
        "commentCount": "9",
        "sharedCount": "25"
      },
      "cover": "http://sns-webpic-qc.xhscdn.com/202604150008/49b8887728edfdc6b50696f173be3407/notes_pre_post/1040g3k831ljnn87j58405nmh6dlg8fomf2tjps8!nc_n_webp_mw_1"
    },
    {
      "id": "69089f4b0000000004028571",
      "xsecToken": "ABT7_Unu8TUvEeVicctYBlbzfw3_lX-P3aF4SvoxzLmxU=",
      "modelType": "note",
      "index": 41,
      "displayTitle": "珠海长隆2天1夜攻略：海洋王国+长隆秀+酒店",
      "type": "normal",
      "user": {
        "userId": "5c6b96f900000000120021dc",
        "nickname": "钱多多吖（打工人户外版）"
      },
      "interactInfo": {
        "likedCount": "68",
        "collectedCount": "73",
        "commentCount": "5",
        "sharedCount": "52"
      },
      "cover": "http://sns-webpic-qc.xhscdn.com/202604150008/5c9184044bffbfbd624a4362be203b03/1040g2sg31oe30cuj5meg5n3birskg8esjefj2bg!nc_n_webp_mw_1"
    },
    {
      "id": "69b272ec000000002202d90a",
      "xsecToken": "ABikBuCyNI1dLmLROeh5IBDMqlq8xI1Exs9hL5-2zoGN8=",
      "modelType": "note",
      "index": 42,
      "displayTitle": "第一次来长隆看这篇就够",
      "type": "normal",
      "user": {
        "userId": "63f63624000000001001e139",
        "nickname": "BADUN"
      },
      "interactInfo": {
        "likedCount": "3702",
        "collectedCount": "5207",
        "commentCount": "123",
        "sharedCount": "1908"
      },
      "cover": "http://sns-webpic-qc.xhscdn.com/202604150008/63dc5a9b8725f589964ddeea735ae14d/1040g2sg31tjppjhnmie05ovm6oi43o9prc8p7v8!nc_n_webp_mw_1"
    },
    {
      "id": "69dcf7ea000000002200c368",
      "xsecToken": "ABJZF46Jk75kY30pt9D-Y9f68wn_q98FaGgclxtpvwVxs=",
      "modelType": "note",
      "index": 43,
      "displayTitle": "",
      "type": "normal",
      "user": {
        "userId": "5f0165e100000000010062a9",
        "nickname": "广珠长隆穿梭巴士乘车指引"
      },
      "interactInfo": {
        "likedCount": "5",
        "collectedCount": "6",
        "commentCount": "0",
        "sharedCount": "4"
      },
      "cover": "http://sns-webpic-qc.xhscdn.com/202604150008/43acacef141b7f1078e378e412ea020e/1040g00831us8e6ttj44g5no1cngg8ol926g1jtg!nc_n_webp_mw_1"
    }
  ],
  "count": 44
}