{
  "feeds": [
    {
      "id": "691e891a000000001e004101",
      "xsecToken": "ABPqodEf3LnbUQLpBcG5jyXr0lXMdosexfCUP-ukPTPd8=",
      "modelType": "note",
      "index": 0,
      "displayTitle": "五道营胡同丨北京小资，文艺citywalk路线",
      "type": "normal",
      "user": {
        "userId": "6287dd75000000002102b7b9",
        "nickname": "冷三岁"
      },
      "interactInfo": {
        "likedCount": "157",
        "collectedCount": "125",
        "commentCount": "6",
        "sharedCount": "111"
      },
      "cover": "http://sns-webpic-qc.xhscdn.com/202604150013/7a3d808a014a888e1aa6cc6141ca4163/notes_pre_post/1040g3k831p3fj3ps2c705ok7rlqoddtptoiveag!nc_n_webp_mw_1"
    },
    {
      "id": "6960f9340000000021031287",
      "xsecToken": "ABSiIFod9wUPgTLqoKKIvWmAQnvhtj_ovRP-agYYXNmRY=",
      "modelType": "note",
      "index": 1,
      "displayTitle": "解锁北京宝藏胡同 | 五道营city walk",
      "type": "normal",
      "user": {
        "userId": "55b8cf5441a2b3161e8d674b",
        "nickname": "京京的漫游记"
      },
      "interactInfo": {
        "likedCount": "126",
        "collectedCount": "93",
        "commentCount": "4",
        "sharedCount": "211"
      },
      "cover": "http://sns-webpic-qc.xhscdn.com/202604150013/2083df8d8df9218371bfb005c16eb80e/notes_pre_post/1040g3k831r4chqstng70410qa47l8pqbc1423og!nc_n_webp_mw_1"
    },
    {
      "id": "6825ced80000000021003178",
      "xsecToken": "ABbKgX1Ta1nsWJhtDevCPak0LeBtBeqLrsEDVUgiiHAmg=",
      "modelType": "note",
      "index": 2,
      "displayTitle": "北京Citywalk天花板|五道营胡同超全攻略",
      "type": "normal",
      "user": {
        "userId": "60be1faf00000000200279c8",
        "nickname": "~橘子🍊"
      },
      "interactInfo": {
        "likedCount": "50",
        "collectedCount": "98",
        "commentCount": "0",
        "sharedCount": "167"
      },
      "cover": "http://sns-webpic-qc.xhscdn.com/202604150013/89df96fcb490464f0284d26e2b803c3c/notes_pre_post/1040g3k031hgjkt07ju6g5o5u3uno4ue895m1bk0!nc_n_webp_mw_1"
    },
    {
      "id": "6960fd3a000000002203254e",
      "xsecToken": "ABSiIFod9wUPgTLqoKKIvWmHFhlj7P7GuSgk3rDHkl4YA=",
      "modelType": "note",
      "index": 3,
      "displayTitle": "北京五道营胡同city walk",
      "type": "normal",
      "user": {
        "userId": "5b0ce60711be100dd019ea79",
        "nickname": "圈圈的北京生活日记"
      },
      "interactInfo": {
        "likedCount": "113",
        "collectedCount": "66",
        "commentCount": "26",
        "sharedCount": "15"
      },
      "cover": "http://sns-webpic-qc.xhscdn.com/202604150013/6bdc39c0a45ab9f513bda8aafb101874/notes_pre_post/1040g3k031r4d1qgnnu3g4a5oc2j0fqjpjbqfod8!nc_n_webp_mw_1"
    },
    {
      "id": "688c32470000000023020b23",
      "xsecToken": "ABGeIbY7WmPyEzDO-3ySQGIJKc3npmR_nD-Wm8yzbU_Zw=",
      "modelType": "note",
      "index": 4,
      "displayTitle": "超级好逛吃的 一条 citywalk 路线🚶‍♀️（上）",
      "type": "normal",
      "user": {
        "userId": "61dd5741000000001000a2dc",
        "nickname": "1 懵"
      },
      "interactInfo": {
        "likedCount": "1524",
        "collectedCount": "1321",
        "commentCount": "15",
        "sharedCount": "1546"
      },
      "cover": "http://sns-webpic-qc.xhscdn.com/202604150013/90952efe6044251b6e05fbd5394bd263/notes_pre_post/1040g3k831kkgiq5i32005oetat0k18mscph52oo!nc_n_webp_mw_1"
    },
    {
      "id": "6973543c0000000022030ac4",
      "xsecToken": "AB7KA6pZ9N5C9PyzN_eGRDoty7527XusaUSg-N9lQjmIc=",
      "modelType": "note",
      "index": 5,
      "displayTitle": "北京中转半天｜胡同citywalk感受老北京韵味",
      "type": "normal",
      "user": {
        "userId": "5ebf82f70000000001000597",
        "nickname": "爱旅行的萌卿酱"
      },
      "interactInfo": {
        "likedCount": "38",
        "collectedCount": "55",
        "commentCount": "0",
        "sharedCount": "33"
      },
      "cover": "http://sns-webpic-qc.xhscdn.com/202604150013/a5c66e4ccaf30a79c4c93bafa36057e1/notes_pre_post/1040g3k831rma8d0b2g005nlvgbrg81cnkd2037o!nc_n_webp_mw_1"
    },
    {
      "id": "db73c97a-857c-4c68-8387-8d7842801eb8#1776183229611",
      "xsecToken": "ABQ0rcHHRx7g2zRILJ1l9v_qN9BrVLDnk0PUn1Mge2bv_e_-OtRcX9bNTg7Tbsr6wKaNPucopGlle-rUlcbq1Eee1Zmw2EI5D15UWgfIvvPkc=",
      "modelType": "hot_query",
      "index": 6,
      "displayTitle": "",
      "type": "",
      "user": {
        "userId": "",
        "nickname": ""
      },
      "interactInfo": {
        "likedCount": "",
        "collectedCount": "",
        "commentCount": "",
        "sharedCount": ""
      }
    },
    {
      "id": "6964f006000000000a02e617",
      "xsecToken": "ABGK8J8UXSw8sMww-xBMzQBz9l9E3HX5rYf_z50Ykt3Y4=",
      "modelType": "note",
      "index": 7,
      "displayTitle": "五道营摇滚School+演出",
      "type": "normal",
      "user": {
        "userId": "5c2ff2c40000000005005355",
        "nickname": "星律"
      },
      "interactInfo": {
        "likedCount": "221",
        "collectedCount": "50",
        "commentCount": "258",
        "sharedCount": "46"
      },
      "cover": "http://sns-webpic-qc.xhscdn.com/202604150013/7c8b3e7a8bd672b55f44d61710196955/notes_pre_post/1040g3k031r87ks2572005n1fub218kqllntgnqg!nc_n_webp_mw_1"
    },
    {
      "id": "69b130dd0000000008032a02",
      "xsecToken": "AB0ILbkHWSCqemPPnQwh95S9MxAEYHphxD4n2SD-yPGZs=",
      "modelType": "note",
      "index": 8,
      "displayTitle": "迄今为止‼北京春天必逛的6️⃣条胡同路线",
      "type": "normal",
      "user": {
        "userId": "5cd976210000000011018f94",
        "nickname": "窝窝带娃超会玩"
      },
      "interactInfo": {
        "likedCount": "2246",
        "collectedCount": "2838",
        "commentCount": "39",
        "sharedCount": "1829"
      },
      "cover": "http://sns-webpic-qc.xhscdn.com/202604150013/47ab40b088074cb847f78052814b32b7/spectrum/1040g0k031timvk5b58505n6peogkb3sk5jm6kl0!nc_n_webp_mw_1"
    },
    {
      "id": "69d63be300000000210386d4",
      "xsecToken": "ABZ_hvCZycEey2T4wraAfj47ABrbvOKdheV_eVOWIOSaQ=",
      "modelType": "note",
      "index": 9,
      "displayTitle": "不用赶场🌸隆福寺到五道营的松弛感路线❗️",
      "type": "normal",
      "user": {
        "userId": "5afd20656b58b72970ba13fd",
        "nickname": "嗨妈&zdp"
      },
      "interactInfo": {
        "likedCount": "41",
        "collectedCount": "35",
        "commentCount": "19",
        "sharedCount": "9"
      },
      "cover": "http://sns-webpic-qc.xhscdn.com/202604150013/6035aa7bb126dec942d57c037cb8f5fa/notes_pre_post/1040g3k831umrdhau2ohg4a5dakg6a4vt7t9aum8!nc_n_webp_mw_1"
    },
    {
      "id": "6921913b000000000d03e922",
      "xsecToken": "ABPczKNjQwtW7d8DWqxXkTgnYyn3o8xZfF4ltohMfeidQ=",
      "modelType": "note",
      "index": 10,
      "displayTitle": "五道营Citywalk",
      "type": "normal",
      "user": {
        "userId": "68484696000000001b019bae",
        "nickname": "肆爺"
      },
      "interactInfo": {
        "likedCount": "2",
        "collectedCount": "0",
        "commentCount": "0",
        "sharedCount": "0"
      },
      "cover": "http://sns-webpic-qc.xhscdn.com/202604150013/18388eff91382e74358d34d177a9456f/1040g2sg31p6eso4u2ufg5q288qb6r6teo9t9hr0!nc_n_webp_mw_1"
    },
    {
      "id": "69cbe5e2000000001e00fe2f",
      "xsecToken": "ABQdpv9goMvg0DoBh21BfY506VdpAdYaC4Wu_xgC0CT5s=",
      "modelType": "note",
      "index": 11,
      "displayTitle": "北京📍雍和宫 五道营胡同 国子监 地坛公园",
      "type": "normal",
      "user": {
        "userId": "5e605cfd00000000010090ef",
        "nickname": "蜜桃乌龙"
      },
      "interactInfo": {
        "likedCount": "48",
        "collectedCount": "42",
        "commentCount": "0",
        "sharedCount": "20"
      },
      "cover": "http://sns-webpic-qc.xhscdn.com/202604150013/05869d04c4caf174944d1d33eb9aafa6/notes_pre_post/1040g3k831ucp7b5a2g705nj0bjug947f59ir5rg!nc_n_webp_mw_1"
    },
    {
      "id": "692eb780000000000d03fe19",
      "xsecToken": "ABiJQYrlFgYzt1Qe1FcO8VwdoDZAil3-DqubFwUB6D_sI=",
      "modelType": "note",
      "index": 12,
      "displayTitle": "12.1实况❗️来五道营就是为了这扇窗🖼️",
      "type": "normal",
      "user": {
        "userId": "6642f8320000000007005f95",
        "nickname": "LuLu的漫游日记"
      },
      "interactInfo": {
        "likedCount": "168",
        "collectedCount": "120",
        "commentCount": "13",
        "sharedCount": "131"
      },
      "cover": "http://sns-webpic-qc.xhscdn.com/202604150013/6636d05879e0ff853eb8c5aab88c627c/notes_pre_post/1040g3k831pj9p4rq4m705pi2v0p1onsl7fp4mr8!nc_n_webp_mw_1"
    },
    {
      "id": "69d7a794000000001e00f7b9",
      "xsecToken": "ABb05MK9Z_uQ6SpW2kx1gvdeo1xc7FFo6EvMK84tV0iis=",
      "modelType": "note",
      "index": 13,
      "displayTitle": "☀️五道营citywalk｜被美食和咖啡治愈的一天",
      "type": "normal",
      "user": {
        "userId": "5db1145e000000000100048a",
        "nickname": "晚风拌糖吃"
      },
      "interactInfo": {
        "likedCount": "8",
        "collectedCount": "3",
        "commentCount": "1",
        "sharedCount": "5"
      },
      "cover": "http://sns-webpic-qc.xhscdn.com/202604150013/6f021b84f6b871fb5f9c43e7345de47e/1040g00831uorii1eii205ndh2hf0814akm4elpg!nc_n_webp_mw_1"
    },
    {
      "id": "69d11a89000000001a02b5cc",
      "xsecToken": "ABiG93V2D0BoC2XVAJDt4jtKZhxgLyQQPkV64AGqyJFWw=",
      "modelType": "note",
      "index": 14,
      "displayTitle": "苏新皓北京同款打卡路线-五道营胡同",
      "type": "normal",
      "user": {
        "userId": "5fc7c8060000000001002067",
        "nickname": "-昂音交响曲-"
      },
      "interactInfo": {
        "likedCount": "11",
        "collectedCount": "5",
        "commentCount": "0",
        "sharedCount": "2"
      },
      "cover": "http://sns-webpic-qc.xhscdn.com/202604150013/92096864acbe5739cd71374de61cfb05/notes_pre_post/1040g3k031uhp8cf3ia605nu7p0308837kj9e1ag!nc_n_webp_mw_1"
    },
    {
      "id": "6983145f000000000e03eb5d",
      "xsecToken": "AB-J2YTsWKhmcNsy0ulbhCMFay_wDiSccN_iG2ltcTfxo=",
      "modelType": "note",
      "index": 15,
      "displayTitle": "五道营胡同｜逛不够的宝藏小店合集",
      "type": "normal",
      "user": {
        "userId": "648a800d000000001c02b3ff",
        "nickname": "阿姆斯特丹"
      },
      "interactInfo": {
        "likedCount": "21",
        "collectedCount": "19",
        "commentCount": "0",
        "sharedCount": "17"
      },
      "cover": "http://sns-webpic-qc.xhscdn.com/202604150013/0aba85e4323a353810521262436d2e33/notes_pre_post/1040g3k831s5mc26c5k6g5p4ag06n5cvv2skfeio!nc_n_webp_mw_1"
    },
    {
      "id": "db73c97a-857c-4c68-8387-8d7842801eb8#1776183229611",
      "xsecToken": "ABQ0rcHHRx7g2zRILJ1l9v_qN9BrVLDnk0PUn1Mge2bv_e_-OtRcX9bNTg7Tbsr6wKaNPucopGlle-rUlcbq1Eee1Zmw2EI5D15UWgfIvvPkc=",
      "modelType": "hot_query",
      "index": 16,
      "displayTitle": "",
      "type": "",
      "user": {
        "userId": "",
        "nickname": ""
      },
      "interactInfo": {
        "likedCount": "",
        "collectedCount": "",
        "commentCount": "",
        "sharedCount": ""
      }
    },
    {
      "id": "690aaf23000000000401737a",
      "xsecToken": "ABCitTGYAexMN75_eKlrWZQ9EftW12Uw1FHNFP5a6BgLg=",
      "modelType": "note",
      "index": 17,
      "displayTitle": "🔥北京五道营保姆级攻略｜吃喝玩乐",
      "type": "normal",
      "user": {
        "userId": "5b7f621a493a8d0001fbb7ca",
        "nickname": "麻鸭鸭带您看世界"
      },
      "interactInfo": {
        "likedCount": "1",
        "collectedCount": "1",
        "commentCount": "0",
        "sharedCount": "4"
      },
      "cover": "http://sns-webpic-qc.xhscdn.com/202604150013/efd5683a7be15ff86625af3641c9c2d6/spectrum/1040g0k031og429oo4s004aitv0h1lduampr0rm8!nc_n_webp_mw_1"
    },
    {
      "id": "6879f115000000001d00e1b8",
      "xsecToken": "ABRYAZaMfQsnEM-enxZt6fVdKyz06bRGQdB5qssitoEPA=",
      "modelType": "note",
      "index": 18,
      "displayTitle": "北京城超有松弛感的宝藏胡同citywalk路线！",
      "type": "normal",
      "user": {
        "userId": "659053240000000022008f17",
        "nickname": "醒醒别睡啦"
      },
      "interactInfo": {
        "likedCount": "102",
        "collectedCount": "110",
        "commentCount": "9",
        "sharedCount": "37"
      },
      "cover": "http://sns-webpic-qc.xhscdn.com/202604150013/197cb526816f4a5ee421d5e6a3b55550/notes_pre_post/1040g3k831k2otdgu30005pcgaci8h3onka0jco8!nc_n_webp_mw_1"
    },
    {
      "id": "69c763c2000000001d0185c8",
      "xsecToken": "ABQwBovKdvW9a0fiT8RtIBnMvxJexmnDQahY854VDJC_Y=",
      "modelType": "note",
      "index": 19,
      "displayTitle": "",
      "type": "normal",
      "user": {
        "userId": "593231155e87e77adab547ea",
        "nickname": "临泉听风的微博"
      },
      "interactInfo": {
        "likedCount": "94",
        "collectedCount": "26",
        "commentCount": "9",
        "sharedCount": "11"
      },
      "cover": "http://sns-webpic-qc.xhscdn.com/202604150013/dd741643c9660079572e40e50e287cfd/1040g2sg31u8cs0ho1ur049i6gbohahva9se4ma8!nc_n_webp_mw_1"
    },
    {
      "id": "691303980000000003013486",
      "xsecToken": "AB6iNBRrtjsQEW1fpsLWb-pip63rihk5DX0zOJJrBDxZs=",
      "modelType": "note",
      "index": 20,
      "displayTitle": "🍂北京Citywalk｜如果只能推荐一条路线",
      "type": "video",
      "user": {
        "userId": "5cc121da0000000017009d46",
        "nickname": "小谁的慢游生活志"
      },
      "interactInfo": {
        "likedCount": "1231",
        "collectedCount": "1627",
        "commentCount": "42",
        "sharedCount": "826"
      },
      "cover": "http://sns-webpic-qc.xhscdn.com/202604150013/897386174a23d1fa53d6dadc74abe87a/1040g00831oo6566g6m005n6147d5p7a64634bu8!nc_n_webp_mw_1"
    },
    {
      "id": "69d0d8660000000023026375",
      "xsecToken": "ABc_kzGs4Fg-diyV-0makWiOcymlrLlJUF7M1xuRfYT5I=",
      "modelType": "note",
      "index": 21,
      "displayTitle": "北京胡同Citywalk天花板✨五道营×北锣鼓巷",
      "type": "normal",
      "user": {
        "userId": "58a6c20182ec391754762365",
        "nickname": "xyxj_nj"
      },
      "interactInfo": {
        "likedCount": "1",
        "collectedCount": "2",
        "commentCount": "2",
        "sharedCount": "2"
      },
      "cover": "http://sns-webpic-qc.xhscdn.com/202604150013/b2474e4153887ab004f9ef17081c28bc/note_pre_post_uhdr/1040g3r831uhkeaj3jg3g495na71028r59vam708!nc_n_webp_mw_1"
    },
    {
      "id": "6832d551000000000303d767",
      "xsecToken": "ABZeRqBjrxPKYSkKRsH2CW2RPF5DjBOU17U65J3gt5QWg=",
      "modelType": "note",
      "index": 22,
      "displayTitle": "北京citywalk(1/100)之五道营胡同",
      "type": "normal",
      "user": {
        "userId": "667ecb0900000000070071cc",
        "nickname": "乐游老太"
      },
      "interactInfo": {
        "likedCount": "135",
        "collectedCount": "109",
        "commentCount": "5",
        "sharedCount": "356"
      },
      "cover": "http://sns-webpic-qc.xhscdn.com/202604150013/05529d7c4b26f62e573c8b1adab36dea/spectrum/1040g34o31hta15923a0g5pjupc4hosecdr66s8g!nc_n_webp_mw_1"
    },
    {
      "id": "689de3e7000000001c03f637",
      "xsecToken": "ABg8L3h0XfVOd-bMbICm70PGOd2YSuTTAJh15wWutdUFg=",
      "modelType": "note",
      "index": 23,
      "displayTitle": "无广！雍和宫Citywalk小众路线🍃（附地图",
      "type": "normal",
      "user": {
        "userId": "6296ea9a000000002102bc27",
        "nickname": "明明是小贾"
      },
      "interactInfo": {
        "likedCount": "4571",
        "collectedCount": "5027",
        "commentCount": "61",
        "sharedCount": "2788"
      },
      "cover": "http://sns-webpic-qc.xhscdn.com/202604150013/368c7482f07b143dec25cf62a2b8af28/notes_pre_post/1040g3k831l5s96ml4q7g5okmtad8df174durico!nc_n_webp_mw_1"
    },
    {
      "id": "6892b7290000000004007eb6",
      "xsecToken": "AB4R5XZnSDCMB38rwmN1iVNg1WFgXSb3dCf3jbiuMk35E=",
      "modelType": "note",
      "index": 24,
      "displayTitle": "五道营｜夜游北京胡同的正确打开方式",
      "type": "normal",
      "user": {
        "userId": "556a93d35894465278679044",
        "nickname": "菁姐说"
      },
      "interactInfo": {
        "likedCount": "293",
        "collectedCount": "225",
        "commentCount": "8",
        "sharedCount": "285"
      },
      "cover": "http://sns-webpic-qc.xhscdn.com/202604150013/e627e5cd88f709c0c6daadfbc038c1d3/1040g2sg31kqv28akiuq040nefc9t7424ki84oj8!nc_n_webp_mw_1"
    },
    {
      "id": "68cc0d57000000000e0228e9",
      "xsecToken": "ABWyJcDwC0sMYZpiEwHGXWXBbXSTYyZ8FfDqOhUoWUzqI=",
      "modelType": "note",
      "index": 25,
      "displayTitle": "五道营｜绝对是北京最文艺的胡同‼️",
      "type": "normal",
      "user": {
        "userId": "676986b40000000018016e70",
        "nickname": "小牛仔"
      },
      "interactInfo": {
        "likedCount": "805",
        "collectedCount": "622",
        "commentCount": "47",
        "sharedCount": "771"
      },
      "cover": "http://sns-webpic-qc.xhscdn.com/202604150013/26975a68038f4a2c8eeb109f7a9292ac/notes_pre_post/1040g3k031miufmi6mg0g5pr9gqq62rjg3qm1j90!nc_n_webp_mw_1"
    },
    {
      "id": "686935b80000000017037661",
      "xsecToken": "ABedXHDcYswgL9p3HijKcJ8J6rJDGYr3yWKxZUzqequbM=",
      "modelType": "note",
      "index": 26,
      "displayTitle": "🫧五道营胡同攻略 | 周末分享",
      "type": "normal",
      "user": {
        "userId": "598f2df050c4b4752f942b4d",
        "nickname": "等你"
      },
      "interactInfo": {
        "likedCount": "21",
        "collectedCount": "17",
        "commentCount": "0",
        "sharedCount": "6"
      },
      "cover": "http://sns-webpic-qc.xhscdn.com/202604150013/bdad24a5e3907a57c63ed39a08406142/notes_pre_post/1040g3k831jidj4cq348049nsnmmv0aqdpuvvdk0!nc_n_webp_mw_1"
    },
    {
      "id": "689e94e6000000001d0376a2",
      "xsecToken": "AB7WHe_auEh4PPAJdukhPi8PZ5cCqWuLtiHjSEfm-rQNQ=",
      "modelType": "note",
      "index": 27,
      "displayTitle": "记不清是第几次在五道营胡同citywalk了🛵",
      "type": "normal",
      "user": {
        "userId": "5e3e91f2000000000100acef",
        "nickname": "V的千千万"
      },
      "interactInfo": {
        "likedCount": "499",
        "collectedCount": "327",
        "commentCount": "12",
        "sharedCount": "116"
      },
      "cover": "http://sns-webpic-qc.xhscdn.com/202604150013/c6d06b3201117ecde7d801bc1dcb963b/notes_pre_post/1040g3k831l6hsu21iul05nhui7p09b7f26m97mo!nc_n_webp_mw_1"
    },
    {
      "id": "cc489755-06f1-4b7a-88ed-a6caa5c9b232#1776183230348",
      "xsecToken": "ABBD6wTrI7tgAQQ-HDKpNxBj3LHcxUGd7WjgDql3QI8yDHaw-X0-96y14biz6BqhLBSqhS6pl0iEJKOQwvbpSALAFzrzg7dtd-TUbpJ4bRK-M=",
      "modelType": "hot_query",
      "index": 28,
      "displayTitle": "",
      "type": "",
      "user": {
        "userId": "",
        "nickname": ""
      },
      "interactInfo": {
        "likedCount": "",
        "collectedCount": "",
        "commentCount": "",
        "sharedCount": ""
      }
    },
    {
      "id": "67c53005000000000602848e",
      "xsecToken": "ABXW3PXXAyTWPeqZ66xndpnbQzhSLvP6ms7QqbxcfrFRY=",
      "modelType": "note",
      "index": 29,
      "displayTitle": "压箱底北京胡同CityWalk！五道营漫游攻略",
      "type": "normal",
      "user": {
        "userId": "661f72a900000000070063f5",
        "nickname": "东东大表哥"
      },
      "interactInfo": {
        "likedCount": "53",
        "collectedCount": "61",
        "commentCount": "3",
        "sharedCount": "40"
      },
      "cover": "http://sns-webpic-qc.xhscdn.com/202604150013/43d6acad424cdf4a27a5bc30891bc84c/spectrum/1040g34o31ei8a3sm0c105pgveakhoovlnsg29no!nc_n_webp_mw_1"
    },
    {
      "id": "67755672000000001301b569",
      "xsecToken": "AB_zw0ElgzvtFnutweikjSVtbRNOtf81_E5ezDcz3Mk8Y=",
      "modelType": "note",
      "index": 30,
      "displayTitle": "雍和宫对面的【五道营胡同】你还没去过吗‼️",
      "type": "normal",
      "user": {
        "userId": "571801ffaed7587d7c9f3872",
        "nickname": "柠蒙茶树菇🍋"
      },
      "interactInfo": {
        "likedCount": "319",
        "collectedCount": "336",
        "commentCount": "2",
        "sharedCount": "158"
      },
      "cover": "http://sns-webpic-qc.xhscdn.com/202604150013/d451c5e8059267d7c9cec33a9db57f01/notes_pre_post/1040g3k031c4913e7160g4854ic0vue3iituluuo!nc_n_webp_mw_1"
    },
    {
      "id": "67c0f7d70000000006029960",
      "xsecToken": "ABusGn5dvgbIX_uMUPy0-RVnpzqatAz-dYFd5TJqFHt4Q=",
      "modelType": "note",
      "index": 31,
      "displayTitle": "迄今为止❗️这是北京最经典胡同Citywalk路线",
      "type": "normal",
      "user": {
        "userId": "5c2237e7000000000701a376",
        "nickname": "冷不少"
      },
      "interactInfo": {
        "likedCount": "609",
        "collectedCount": "847",
        "commentCount": "38",
        "sharedCount": "433"
      },
      "cover": "http://sns-webpic-qc.xhscdn.com/202604150013/1aef673fd68cb4c07e0a5eb5ca10694d/1040g2sg31eh0nt35h0a05n126vjhr8rmefbs388!nc_n_webp_mw_1"
    },
    {
      "id": "69de1d39000000001a03548e",
      "xsecToken": "ABlDpFpdlGK_t728jWSS3SfzV_Ze54E0NZwYzb9vknY2M=",
      "modelType": "note",
      "index": 32,
      "displayTitle": "五道营78号真不是景点，听店主说心里话💬",
      "type": "normal",
      "user": {
        "userId": "61f7b57f000000001000f12a",
        "nickname": "拉拉风在五道营"
      },
      "interactInfo": {
        "likedCount": "1",
        "collectedCount": "0",
        "commentCount": "0",
        "sharedCount": "0"
      },
      "cover": "http://sns-webpic-qc.xhscdn.com/202604150013/f815914a6d2f70fafd3a32146b588aa0/notes_pre_post/1040g3k831uug13ma2g705ofnmlvk1s9agv024sg!nc_n_webp_mw_1"
    },
    {
      "id": "67c1c3b6000000002902dadb",
      "xsecToken": "ABi4yOb4bClBCpIRPSmpRYUR2MP-0CISVwT-FQID350DA=",
      "modelType": "note",
      "index": 33,
      "displayTitle": "北京citywalk，五道营-国子监-东四，附路线图",
      "type": "normal",
      "user": {
        "userId": "5ddcf3e600000000010023f5",
        "nickname": "北京去哪儿玩"
      },
      "interactInfo": {
        "likedCount": "570",
        "collectedCount": "704",
        "commentCount": "6",
        "sharedCount": "591"
      },
      "cover": "http://sns-webpic-qc.xhscdn.com/202604150013/0bed0ab82e2ac281ba4562c4cbfa7a32/notes_pre_post/1040g3k031eers911gm1g5nesufj088vlbi61410!nc_n_webp_mw_1"
    },
    {
      "id": "69ca4c3c000000002103b782",
      "xsecToken": "ABJIh-R0-6lJfMbZDH5lWBApNi8tPn-IwDH9qvdDKJmV0=",
      "modelType": "note",
      "index": 34,
      "displayTitle": "北京必逛的6️⃣条胡同路线❗️绝美",
      "type": "normal",
      "user": {
        "userId": "5505b95b2e1d93482a4b3444",
        "nickname": "大圆圆"
      },
      "interactInfo": {
        "likedCount": "283",
        "collectedCount": "449",
        "commentCount": "14",
        "sharedCount": "236"
      },
      "cover": "http://sns-webpic-qc.xhscdn.com/202604150013/72f9f82a74d98e5daddebe4de9a1eb28/1040g00831ub80f5niqe04067n1slmd24j4bbrvo!nc_n_webp_mw_1"
    },
    {
      "id": "69a1509e000000001d010b24",
      "xsecToken": "ABEiZAfR4Rr2taZgJDq7jAGAz4tBFKzf-6LB7ghHL0P2Q=",
      "modelType": "note",
      "index": 35,
      "displayTitle": "北京东四逛吃3km雍和宫出发🔥全程不绕",
      "type": "normal",
      "user": {
        "userId": "66adb061000000001d0217e6",
        "nickname": "和饲养员吃遍天下"
      },
      "interactInfo": {
        "likedCount": "19",
        "collectedCount": "12",
        "commentCount": "1",
        "sharedCount": "5"
      },
      "cover": "http://sns-webpic-qc.xhscdn.com/202604150013/31e271cec5ea892cd1e118593b29ba0c/1040g2sg31t2ri1kq5sk05pldm1gnc5v615fgkto!nc_n_webp_mw_1"
    },
    {
      "id": "6845aa5d000000001101fd87",
      "xsecToken": "ABbbUmwEKHdbiQiyLurlTVreQg1pkFLBl1obO0oBYEgJY=",
      "modelType": "note",
      "index": 36,
      "displayTitle": "【City walk】南锣鼓巷+五道营半日游💗",
      "type": "normal",
      "user": {
        "userId": "5a8b85a511be1077fe08af65",
        "nickname": "白了白白"
      },
      "interactInfo": {
        "likedCount": "10",
        "collectedCount": "8",
        "commentCount": "1",
        "sharedCount": "6"
      },
      "cover": "http://sns-webpic-qc.xhscdn.com/202604150013/59250f5df7a06e68a531858ea0240516/notes_pre_post/1040g3k031ifmoaolga0g4a1k3u2qbbr5mid7l28!nc_n_webp_mw_1"
    },
    {
      "id": "69d368fb000000001a02351d",
      "xsecToken": "AB0YiiStHXcPT3Kj8pXzfsiKgLp_sjjy3zzTS9qFhGbcc=",
      "modelType": "note",
      "index": 37,
      "displayTitle": "迄今为止‼北京超适合citywalk🌸赏花路线",
      "type": "normal",
      "user": {
        "userId": "5cd976210000000011018f94",
        "nickname": "窝窝带娃超会玩"
      },
      "interactInfo": {
        "likedCount": "68",
        "collectedCount": "45",
        "commentCount": "2",
        "sharedCount": "54"
      },
      "cover": "http://sns-webpic-qc.xhscdn.com/202604150013/a5dbb905284820c61c37b965b9470054/notes_pre_post/1040g3k831uk4pk312o005n6peogkb3skk3f9cug!nc_n_webp_mw_1"
    },
    {
      "id": "cc489755-06f1-4b7a-88ed-a6caa5c9b232#1776183230348",
      "xsecToken": "ABBD6wTrI7tgAQQ-HDKpNxBj3LHcxUGd7WjgDql3QI8yDHaw-X0-96y14biz6BqhLBSqhS6pl0iEJKOQwvbpSALAFzrzg7dtd-TUbpJ4bRK-M=",
      "modelType": "hot_query",
      "index": 38,
      "displayTitle": "",
      "type": "",
      "user": {
        "userId": "",
        "nickname": ""
      },
      "interactInfo": {
        "likedCount": "",
        "collectedCount": "",
        "commentCount": "",
        "sharedCount": ""
      }
    },
    {
      "id": "69de0181000000001f000650",
      "xsecToken": "ABlDpFpdlGK_t728jWSS3Sf7zZ9R-ZUXlK3i64qdIWO20=",
      "modelType": "note",
      "index": 39,
      "displayTitle": "北京胡同walk｜藏着老北京的灵魂",
      "type": "normal",
      "user": {
        "userId": "69a15c780000000021009ad1",
        "nickname": "夏夏带你转北京"
      },
      "interactInfo": {
        "likedCount": "6",
        "collectedCount": "5",
        "commentCount": "0",
        "sharedCount": "1"
      },
      "cover": "http://sns-webpic-qc.xhscdn.com/202604150013/3b1d1e1437ce430680d705c46d1ee719/notes_pre_post/1040g3k031uuc015kjqq05qd1bhs896mh3p4r2j0!nc_n_webp_mw_1"
    },
    {
      "id": "6950a25c000000001f00fa6b",
      "xsecToken": "ABt7UdWfK-ZxhCUCp-xn10b6ojZT1NTa1ukPUMdtg7XfE=",
      "modelType": "note",
      "index": 40,
      "displayTitle": "迄今！北京我最爱的胡同citywalk路线！附机位",
      "type": "normal",
      "user": {
        "userId": "5c2237e7000000000701a376",
        "nickname": "冷不少"
      },
      "interactInfo": {
        "likedCount": "482",
        "collectedCount": "493",
        "commentCount": "103",
        "sharedCount": "275"
      },
      "cover": "http://sns-webpic-qc.xhscdn.com/202604150013/a7b010361b7ad1348af40ea199d75146/notes_uhdr/1040g3qg31qmph3qi0a005n126vjhr8rmiorefp0!nc_n_webp_mw_1"
    },
    {
      "id": "694962b5000000001b024c57",
      "xsecToken": "ABnvcFu_ncMj7lgCBzA9P7J1Ytx-roKNoNPGjPWuWJc5E=",
      "modelType": "note",
      "index": 41,
      "displayTitle": "北京自由行，1日超好逛city walk 路线！",
      "type": "normal",
      "user": {
        "userId": "5481b808d6e4a96903ed68a2",
        "nickname": "峰蜜"
      },
      "interactInfo": {
        "likedCount": "102",
        "collectedCount": "87",
        "commentCount": "0",
        "sharedCount": "41"
      },
      "cover": "http://sns-webpic-qc.xhscdn.com/202604150013/c9cdf1b0797be3edc5c176870e12ccc7/notes_pre_post/1040g3k031qda55q0g050400ps5s0gq5270uffp0!nc_n_webp_mw_1"
    },
    {
      "id": "689af093000000001d0150e7",
      "xsecToken": "ABQgktryhBOa9kSMKarG5VAy_dvqOagblcEtACUEHt3Ys=",
      "modelType": "note",
      "index": 42,
      "displayTitle": "📸 五道营胡同扫街指南｜600米逛吃拍全攻略！",
      "type": "normal",
      "user": {
        "userId": "5e81cd330000000001008bf2",
        "nickname": "DK"
      },
      "interactInfo": {
        "likedCount": "27",
        "collectedCount": "22",
        "commentCount": "0",
        "sharedCount": "16"
      },
      "cover": "http://sns-webpic-qc.xhscdn.com/202604150013/28e5002e5833e23fe6647ba18ed652a7/1040g2sg31l303f0ajq7g5nk1pkpg92vig6acpb8!nc_n_webp_mw_1"
    },
    {
      "id": "69b287940000000026031bfc",
      "xsecToken": "ABikBuCyNI1dLmLROeh5IBDK9ipXPoDjzXxu0FZai9CsU=",
      "modelType": "note",
      "index": 43,
      "displayTitle": "雍和宫出来记得去对面五道营胡同📷",
      "type": "normal",
      "user": {
        "userId": "6002e534000000000101eda8",
        "nickname": "侈蒽陈"
      },
      "interactInfo": {
        "likedCount": "280",
        "collectedCount": "68",
        "commentCount": "18",
        "sharedCount": "5"
      },
      "cover": "http://sns-webpic-qc.xhscdn.com/202604150013/16886221f25d803e45528044c3928a22/1040g00831tk18nrumo005o02skq0brd874r30u0!nc_n_webp_mw_1"
    }
  ],
  "count": 44
}